main.py
agentsphere_python_cli-0.1.0.dist-info/METADATA
agentsphere_python_cli-0.1.0.dist-info/WHEEL
agentsphere_python_cli-0.1.0.dist-info/entry_points.txt
agentsphere_python_cli-0.1.0.dist-info/top_level.txt
agentsphere_python_cli-0.1.0.dist-info/RECORD
