Metadata-Version: 2.4
Name: agentsphere-python-cli
Version: 0.1.0
Summary: CLI tool for connecting to AgentSphere sandboxes with SSH-like functionality
Requires-Python: >=3.12
Requires-Dist: agentsphere==0.1.6
Requires-Dist: click>=8.0.0
Requires-Dist: logging>=0.4.9.6
Requires-Dist: rich>=13.0.0
